setup.py
stripe/__init__.py
stripe/api_requestor.py
stripe/error.py
stripe/http_client.py
stripe/importer.py
stripe/multipart_data_generator.py
stripe/oauth.py
stripe/resource.py
stripe/util.py
stripe/version.py
txstripe/__init__.py
txstripe/error.py
txstripe/resource.py
txstripe/util.py
txstripe.egg-info/PKG-INFO
txstripe.egg-info/SOURCES.txt
txstripe.egg-info/dependency_links.txt
txstripe.egg-info/requires.txt
txstripe.egg-info/top_level.txt