Metadata-Version: 1.1
Name: txstripe
Version: 0.1.0
Summary: Stripe Twisted bindings
Home-page: https://github.com/lextoumbourou/txstripe
Author: Lex Toumbourou
Author-email: lextoumbourou@gmail.com
License: UNKNOWN
Platform: UNKNOWN
Classifier: Intended Audience :: Developers
Classifier: License :: OSI Approved :: MIT License
Classifier: Operating System :: OS Independent
Classifier: Programming Language :: Python
Classifier: Programming Language :: Python :: 2
Classifier: Programming Language :: Python :: 2.6
Classifier: Programming Language :: Python :: 2.7
Classifier: Topic :: Software Development :: Libraries :: Python Modules
